JPRBH/__init__.py
JPRBH/add_albums.py
JPRBH/create_table.py
JPRBH/data.txt
JPRBH/functions.py
JPRBH/get_albums.py
JPRBH/initialize.py
JPRBH/readfile.py
JPRBH/test/__init__.py
JPRBH-0.0.6.dist-info/LICENSE
JPRBH-0.0.6.dist-info/METADATA
JPRBH-0.0.6.dist-info/WHEEL
JPRBH-0.0.6.dist-info/top_level.txt
JPRBH-0.0.6.dist-info/RECORD
