Metadata-Version: 2.1
Name: JPRBH
Version: 0.0.6
Summary: JPR Bayesian Health Code Test Submission
Home-page: https://github.com/johnpatrickroach/JPRBH
Author: John Patrick Roach
Author-email: contact@johnpatrickroach.com
License: UNKNOWN
Platform: UNKNOWN
Classifier: Programming Language :: Python :: 3
Classifier: License :: OSI Approved :: MIT License
Classifier: Operating System :: OS Independent
Requires-Python: >=3.8
